messi_nmr/__init__.py
messi_nmr/__main__.py
messi_nmr/messi_nmr.py
messi_nmr/Example_messi_nmr/01_RSR_Levo01_OPTB_energy_smdb.log
messi_nmr/Example_messi_nmr/01_RSR_Levo01_OPTB_nmr.log
messi_nmr/Example_messi_nmr/01_RSR_Levo02_OPTB_energy_smdb.log
messi_nmr/Example_messi_nmr/01_RSR_Levo02_OPTB_nmr.log
messi_nmr/Example_messi_nmr/01_RSR_Levo03_OPTB_energy_smdb.log
messi_nmr/Example_messi_nmr/01_RSR_Levo03_OPTB_nmr.log
messi_nmr/Example_messi_nmr/01_RSR_Levo04_OPTB_energy_smdb.log
messi_nmr/Example_messi_nmr/01_RSR_Levo04_OPTB_nmr.log
messi_nmr/Example_messi_nmr/01_RSR_Levo05_OPTB_energy_smdb.log
messi_nmr/Example_messi_nmr/01_RSR_Levo05_OPTB_nmr.log
messi_nmr/Example_messi_nmr/01_RSR_Levo06_OPTB_energy_smdb.log
messi_nmr/Example_messi_nmr/01_RSR_Levo06_OPTB_nmr.log
messi_nmr/Example_messi_nmr/01_RSR_Levo07_OPTB_energy_smdb.log
messi_nmr/Example_messi_nmr/01_RSR_Levo07_OPTB_nmr.log
messi_nmr/Example_messi_nmr/01_RSR_Levo08_OPTB_energy_smdb.log
messi_nmr/Example_messi_nmr/01_RSR_Levo08_OPTB_nmr.log
messi_nmr/Example_messi_nmr/01_RSR_Levo09_OPTB_energy_smdb.log
messi_nmr/Example_messi_nmr/01_RSR_Levo09_OPTB_nmr.log
messi_nmr/Example_messi_nmr/01_RSR_Levo10_OPTB_energy_smdb.log
messi_nmr/Example_messi_nmr/01_RSR_Levo10_OPTB_nmr.log
messi_nmr/Example_messi_nmr/01_RSR_Levo11_OPTB_energy_smdb.log
messi_nmr/Example_messi_nmr/01_RSR_Levo11_OPTB_nmr.log
messi_nmr/Example_messi_nmr/01_RSR_Levo12_OPTB_energy_smdb.log
messi_nmr/Example_messi_nmr/01_RSR_Levo12_OPTB_nmr.log
messi_nmr/Example_messi_nmr/01_RSR_Levo13_OPTB_energy_smdb.log
messi_nmr/Example_messi_nmr/01_RSR_Levo13_OPTB_nmr.log
messi_nmr/Example_messi_nmr/01_RSR_Levo14_OPTB_energy_smdb.log
messi_nmr/Example_messi_nmr/01_RSR_Levo14_OPTB_nmr.log
messi_nmr/Example_messi_nmr/01_RSR_Levo15_OPTB_energy_smdb.log
messi_nmr/Example_messi_nmr/01_RSR_Levo15_OPTB_nmr.log
messi_nmr/Example_messi_nmr/01_RSR_Levo16_OPTB_energy_smdb.log
messi_nmr/Example_messi_nmr/01_RSR_Levo16_OPTB_nmr.log
messi_nmr-0.1.14.dist-info/LICENCE
messi_nmr-0.1.14.dist-info/METADATA
messi_nmr-0.1.14.dist-info/WHEEL
messi_nmr-0.1.14.dist-info/entry_points.txt
messi_nmr-0.1.14.dist-info/top_level.txt
messi_nmr-0.1.14.dist-info/RECORD
